odoo/addons/website_sale_attribute_filter_multiselect/README.rst
odoo/addons/website_sale_attribute_filter_multiselect/__init__.py
odoo/addons/website_sale_attribute_filter_multiselect/__manifest__.py
odoo/addons/website_sale_attribute_filter_multiselect/i18n/es.po
odoo/addons/website_sale_attribute_filter_multiselect/i18n/it.po
odoo/addons/website_sale_attribute_filter_multiselect/i18n/website_sale_attribute_filter_multiselect.pot
odoo/addons/website_sale_attribute_filter_multiselect/models/__init__.py
odoo/addons/website_sale_attribute_filter_multiselect/models/product_attribute.py
odoo/addons/website_sale_attribute_filter_multiselect/readme/CONFIGURE.rst
odoo/addons/website_sale_attribute_filter_multiselect/readme/CONTRIBUTORS.rst
odoo/addons/website_sale_attribute_filter_multiselect/readme/CREDITS.rst
odoo/addons/website_sale_attribute_filter_multiselect/readme/DESCRIPTION.rst
odoo/addons/website_sale_attribute_filter_multiselect/readme/USAGE.rst
odoo/addons/website_sale_attribute_filter_multiselect/static/description/icon.png
odoo/addons/website_sale_attribute_filter_multiselect/static/description/index.html
odoo/addons/website_sale_attribute_filter_multiselect/static/src/js/website_sale.js
odoo/addons/website_sale_attribute_filter_multiselect/static/src/lib/multiple-select/multiple-select-locale-all.js
odoo/addons/website_sale_attribute_filter_multiselect/static/src/lib/multiple-select/multiple-select.css
odoo/addons/website_sale_attribute_filter_multiselect/static/src/lib/multiple-select/multiple-select.js
odoo/addons/website_sale_attribute_filter_multiselect/static/src/scss/website_sale.scss
odoo/addons/website_sale_attribute_filter_multiselect/templates/sale.xml
odoo/addons/website_sale_attribute_filter_multiselect/templates/website_sale.xml
odoo_addon_website_sale_attribute_filter_multiselect-16.0.1.0.0.6.dist-info/METADATA
odoo_addon_website_sale_attribute_filter_multiselect-16.0.1.0.0.6.dist-info/WHEEL
odoo_addon_website_sale_attribute_filter_multiselect-16.0.1.0.0.6.dist-info/top_level.txt
odoo_addon_website_sale_attribute_filter_multiselect-16.0.1.0.0.6.dist-info/RECORD
